nbdev-extensions/__init__.py
nbdev-extensions/_modidx.py
nbdev-extensions/mknb.py
nbdev_extensions/__init__.py
nbdev_extensions/_modidx.py
nbdev_extensions/codenotes.py
nbdev_extensions/mknb.py
nbdev_extensions/tagmaker.py
nbdev_extensions-0.1.0.dist-info/.ipynb_checkpoints/entry_points-checkpoint.txt
nbdev_extensions-0.1.0.dist-info/LICENSE
nbdev_extensions-0.1.0.dist-info/METADATA
nbdev_extensions-0.1.0.dist-info/WHEEL
nbdev_extensions-0.1.0.dist-info/entry_points.txt
nbdev_extensions-0.1.0.dist-info/top_level.txt
nbdev_extensions-0.1.0.dist-info/RECORD
