Metadata-Version: 2.1
Name: nbdev-extensions
Version: 0.1.0
Summary: Cool nbdev extensions I've thought of
Home-page: https://github.com/muellerzr/nbdev-extensions/
Author: Zachary Mueller
Author-email: muellerzr@gmail.com
License: Apache Software License 2.0
Keywords: nbdev extensions
Classifier: Development Status :: 3 - Alpha
Classifier: Intended Audience :: Developers
Classifier: Natural Language :: English
Classifier: Programming Language :: Python :: 3.7
Classifier: Programming Language :: Python :: 3.8
Classifier: Programming Language :: Python :: 3.9
Classifier: Programming Language :: Python :: 3.10
Classifier: License :: OSI Approved :: Apache Software License
Requires-Python: >=3.7
License-File: LICENSE
Requires-Dist: nbdev (<3,>=2.0.0)
Provides-Extra: dev
